mlkit/__init__.py
mlkit/_nbdev.py
mlkit/core.py
ml_kit-0.0.1.dist-info/LICENSE
ml_kit-0.0.1.dist-info/METADATA
ml_kit-0.0.1.dist-info/WHEEL
ml_kit-0.0.1.dist-info/entry_points.txt
ml_kit-0.0.1.dist-info/top_level.txt
ml_kit-0.0.1.dist-info/RECORD
